pypivoter-0.1.0.dist-info/METADATA
pypivoter-0.1.0.dist-info/WHEEL
pypivoter-0.1.0.dist-info/top_level.txt
pypivoter-0.1.0.dist-info/RECORD
pypivoter-0.1.0.dist-info/LICENSE.txt
pypivoter/degeneracy_cliques.cpython-39-x86_64-linux-gnu.so
pypivoter/degeneracy_helper.pxd
pypivoter/degeneracy_helper.cpython-39-x86_64-linux-gnu.so
pypivoter/__init__.py
