Metadata-Version: 2.1
Name: pypivoter
Version: 0.1.0
Summary: Count or list the cliques in a graph using the Pivoter algorithm.
Home-page: https://github.com/rckormos/PyPivoter
Author: Rian Kormos
Author-email: rian.kormos@gmail.com
License: MIT
Project-URL: Documentation, https://github.com/rckormos/PyPivoter
Project-URL: Code, https://github.com/rckormos/PyPivoter
Project-URL: Issue tracker, https://github.com/rckormos/PyPivoter/issues
Platform: UNKNOWN
Classifier: Development Status :: 1 - Planning
Classifier: License :: OSI Approved :: MIT License
Classifier: Intended Audience :: Education
Classifier: Intended Audience :: Science/Research
Classifier: Topic :: Scientific/Engineering
Classifier: Natural Language :: English
Classifier: Operating System :: OS Independent
Classifier: Programming Language :: C
Classifier: Programming Language :: Cython
Classifier: Programming Language :: Python
Classifier: Programming Language :: Python :: 3
Classifier: Programming Language :: Python :: 3.4
Classifier: Programming Language :: Python :: 3.5
Classifier: Programming Language :: Python :: 3.6
Classifier: Programming Language :: Python :: 3.7
Classifier: Programming Language :: Python :: 3 :: Only
Classifier: Programming Language :: Python :: Implementation :: CPython
Requires-Python: >=3.4
License-File: LICENSE.txt
Requires-Dist: numpy (>1.5.0)
